norman/__init__.py
norman/__main__.py
norman/consts.py
norman/norman_dataplane.py
norman/norman_pktgen.py
norman_dp-0.1.1.dist-info/LICENSE
norman_dp-0.1.1.dist-info/METADATA
norman_dp-0.1.1.dist-info/WHEEL
norman_dp-0.1.1.dist-info/entry_points.txt
norman_dp-0.1.1.dist-info/top_level.txt
norman_dp-0.1.1.dist-info/RECORD
