Metadata-Version: 2.1
Name: norman-dp
Version: 0.1.1
Summary: Python frontend for the Norman dataplane.
Home-page: https://github.com/hsadok/norman/frontend
Author: Hugo Sadok
Author-email: sadok@cmu.edu
License: BSD
Download-URL: https://github.com/hsadok/norman
Keywords: network,norman,dataplane
Platform: UNKNOWN
Classifier: Development Status :: 4 - Beta
Classifier: Intended Audience :: Science/Research
Classifier: License :: OSI Approved :: BSD License
Classifier: Natural Language :: English
Classifier: Programming Language :: Python
Classifier: Programming Language :: Python :: 3
Classifier: Programming Language :: Python :: 3.6
Classifier: Programming Language :: Python :: 3.7
Classifier: Programming Language :: Python :: 3.8
Classifier: Programming Language :: Python :: 3.9
Classifier: Programming Language :: Python :: 3.10
Classifier: Topic :: System :: Networking
Classifier: Topic :: System :: Systems Administration
Requires-Python: >=3.6
Requires-Dist: click (>=8.0)
Requires-Dist: netexp (==0.1.8)
Requires-Dist: tqdm
